zeta.py
zeta_cli-1.0.9.dist-info/licenses/LICENSE
zeta_cli-1.0.9.dist-info/METADATA
zeta_cli-1.0.9.dist-info/WHEEL
zeta_cli-1.0.9.dist-info/entry_points.txt
zeta_cli-1.0.9.dist-info/top_level.txt
zeta_cli-1.0.9.dist-info/RECORD
