Metadata-Version: 2.4
Name: zeta-cli
Version: 1.0.9
Summary: ZETA: the most accessible AI terminal agent.
Home-page: https://github.com/SukinShetty/Zeta-CLI
Author: Sukin Shetty
Author-email: Sukin Shetty <sukin.shetty8@gmail.com>
License: Apache-2.0
Project-URL: Homepage, https://github.com/SukinShetty/Zeta-CLI
Project-URL: Documentation, https://github.com/SukinShetty/Zeta-CLI#readme
Project-URL: Repository, https://github.com/SukinShetty/Zeta-CLI
Project-URL: Issues, https://github.com/SukinShetty/Zeta-CLI/issues
Keywords: cli,ai,terminal,agent,llm,langchain
Classifier: Development Status :: 4 - Beta
Classifier: Intended Audience :: Developers
Classifier: Intended Audience :: End Users/Desktop
Classifier: License :: OSI Approved :: Apache Software License
Classifier: Programming Language :: Python :: 3
Classifier: Programming Language :: Python :: 3.9
Classifier: Programming Language :: Python :: 3.10
Classifier: Programming Language :: Python :: 3.11
Classifier: Programming Language :: Python :: 3.12
Classifier: Topic :: Software Development :: Libraries :: Python Modules
Classifier: Topic :: Utilities
Requires-Python: >=3.8
License-File: LICENSE
Requires-Dist: click>=8.0.0
Requires-Dist: rich>=14.0.0
Requires-Dist: langchain>=0.1.0
Requires-Dist: langchain-community>=0.0.1
Requires-Dist: langgraph>=0.0.1
Requires-Dist: langchain-ollama>=0.1.0
Provides-Extra: test
Requires-Dist: pytest>=7.0.0; extra == "test"
Requires-Dist: pytest-mock>=3.10.0; extra == "test"
Requires-Dist: pytest-cov>=4.0.0; extra == "test"
Requires-Dist: pytest-timeout>=2.1.0; extra == "test"
Provides-Extra: openai
Requires-Dist: langchain-openai>=1.0.0; extra == "openai"
Provides-Extra: anthropic
Requires-Dist: langchain-anthropic>=1.0.0; extra == "anthropic"
Provides-Extra: google
Requires-Dist: langchain-google-genai>=1.0.0; extra == "google"
Provides-Extra: all
Requires-Dist: langchain-openai>=1.0.0; extra == "all"
Requires-Dist: langchain-anthropic>=1.0.0; extra == "all"
Requires-Dist: langchain-google-genai>=1.0.0; extra == "all"
Dynamic: author
Dynamic: home-page
Dynamic: license-file
Dynamic: requires-python
